solentra/__init__.py
solentra/agent.py
solentra/social.py
solentra/tools.py
solentra-1.0.0.dist-info/licenses/LICENSE
solentra-1.0.0.dist-info/METADATA
solentra-1.0.0.dist-info/WHEEL
solentra-1.0.0.dist-info/top_level.txt
solentra-1.0.0.dist-info/RECORD
