Metadata-Version: 2.4
Name: solentra
Version: 1.0.0
Summary: A powerful Python package for creating science-themed AI agents
Home-page: https://github.com/solentra/solentra
Author: Solentra
Author-email: solentrasol@gmail.com
Classifier: Development Status :: 3 - Alpha
Classifier: Intended Audience :: Science/Research
Classifier: License :: OSI Approved :: MIT License
Classifier: Programming Language :: Python :: 3
Classifier: Programming Language :: Python :: 3.8
Classifier: Programming Language :: Python :: 3.9
Classifier: Programming Language :: Python :: 3.10
Classifier: Topic :: Software Development :: Libraries :: Python Modules
Classifier: Topic :: Software Development :: Libraries :: Application Frameworks
Classifier: Topic :: Scientific/Engineering :: Artificial Intelligence
Classifier: Topic :: Software Development :: Libraries :: Python Modules
Classifier: Topic :: System :: Distributed Computing
Requires-Python: >=3.8
License-File: LICENSE
Requires-Dist: numpy>=1.21.0
Requires-Dist: pandas>=1.3.0
Requires-Dist: scikit-learn>=0.24.0
Requires-Dist: transformers>=4.5.0
Requires-Dist: requests>=2.25.0
Requires-Dist: beautifulsoup4>=4.9.0
Requires-Dist: arxiv>=1.0.0
Requires-Dist: tweepy>=4.0.0
Requires-Dist: python-dotenv>=0.19.0
Requires-Dist: tqdm>=4.62.0
Requires-Dist: matplotlib>=3.4.0
Requires-Dist: seaborn>=0.11.0
Requires-Dist: jupyter>=1.0.0
Requires-Dist: ipython>=7.0.0
Requires-Dist: pytest>=6.2.0
Requires-Dist: black>=21.5b2
Requires-Dist: isort>=5.9.0
Requires-Dist: flake8>=3.9.0
Requires-Dist: mypy>=0.910
Requires-Dist: plotly>=5.0.0
Requires-Dist: openai>=1.0.0
Requires-Dist: GitPython>=3.1.0
Requires-Dist: markdown2>=2.4.0
Requires-Dist: PyPDF2>=3.0.0
Requires-Dist: networkx>=2.8.0
Requires-Dist: nbformat>=5.7.0
Requires-Dist: PyYAML>=6.0.0
Provides-Extra: dev
Requires-Dist: pytest>=6.2.0; extra == "dev"
Requires-Dist: black>=21.5b2; extra == "dev"
Requires-Dist: isort>=5.9.0; extra == "dev"
Requires-Dist: flake8>=3.9.0; extra == "dev"
Requires-Dist: mypy>=0.910; extra == "dev"
Requires-Dist: jupyter>=1.0.0; extra == "dev"
Requires-Dist: ipython>=7.0.0; extra == "dev"
Dynamic: author
Dynamic: author-email
Dynamic: classifier
Dynamic: description
Dynamic: description-content-type
Dynamic: home-page
Dynamic: license-file
Dynamic: provides-extra
Dynamic: requires-dist
Dynamic: requires-python
Dynamic: summary
